nnero/__init__.py
nnero/analysis.py
nnero/astrophysics.py
nnero/classifier.py
nnero/constants.py
nnero/cosmology.py
nnero/data.py
nnero/interpolator.py
nnero/mcmc.py
nnero/network.py
nnero/predictor.py
nnero/regressor.py
nnero/lkl_data/UVData.pkl
nnero/nn_data/DefaultClassifier_loss.npz
nnero/nn_data/DefaultClassifier_metadata.npz
nnero/nn_data/DefaultClassifier_partition.npz
nnero/nn_data/DefaultClassifier_struct.npy
nnero/nn_data/DefaultClassifier_weights.pth
nnero/nn_data/DefaultRegressor_loss.npz
nnero/nn_data/DefaultRegressor_metadata.npz
nnero/nn_data/DefaultRegressor_partition.npz
nnero/nn_data/DefaultRegressor_struct.npy
nnero/nn_data/DefaultRegressor_weights.pth
nnero-1.0.1.dist-info/LICENSE
nnero-1.0.1.dist-info/METADATA
nnero-1.0.1.dist-info/WHEEL
nnero-1.0.1.dist-info/top_level.txt
nnero-1.0.1.dist-info/RECORD
