Metadata-Version: 2.2
Name: nnero
Version: 1.0.1
Summary: Neural-Network emulator for Reionization and Optical depth
Author-email: Gaétan Facchinetti <gaetanfacc@gmail.com>
License:                     GNU GENERAL PUBLIC LICENSE
Project-URL: Homepage, https://github.com/gaetanfacchinetti/NNERO
Keywords: cosmology,machine learning,reionization
Classifier: License :: OSI Approved :: GNU General Public License v3 (GPLv3)
Classifier: Programming Language :: Python
Classifier: Programming Language :: Python :: 3
Classifier: Operating System :: Unix
Classifier: Operating System :: MacOS :: MacOS X
Classifier: Operating System :: Microsoft :: Windows
Requires-Python: >=3.11
License-File: LICENSE
Requires-Dist: numpy>=1.16.5
Requires-Dist: scipy
Requires-Dist: torch
